LICENSE
README.md
pyproject.toml
setup.py
cohdl_sim/__init__.py
cohdl_sim/_base_proxy_port.py
cohdl_sim/_base_simulation.py
cohdl_sim/_base_simulation.pyi
cohdl_sim/_build_cache.py
cohdl_sim/_proxy_port.py
cohdl_sim/_simulation.py
cohdl_sim/_simulation.pyi
cohdl_sim.egg-info/PKG-INFO
cohdl_sim.egg-info/SOURCES.txt
cohdl_sim.egg-info/dependency_links.txt
cohdl_sim.egg-info/requires.txt
cohdl_sim.egg-info/top_level.txt
cohdl_sim/axi/axi4_light.py
cohdl_sim/axi/axi4_light.pyi
cohdl_sim/ghdl_sim/__init__.py
cohdl_sim/ghdl_sim/_build_simulation.py
cohdl_sim/ghdl_sim/_proxy_port.py
cohdl_sim/ghdl_sim/_simulation.py
cohdl_sim/ghdl_sim/_simulation.pyi
cpp/cohdl_sim_ghdl_interface/ghdl_cohdl_interface.cpp
cpp/cohdl_sim_ghdl_interface/ghdl_cohdl_interface.hpp
cpp/cohdl_sim_ghdl_interface/main.cpp
playground/01_playground.py