Metadata-Version: 2.4
Name: cohdl_sim
Version: 0.2.4
Summary: Simulation support library for CoHDL, based on cocotb
Author: Alexander Forster
Author-email: Alexander Forster <alexander.forster123@gmail.com>
Project-URL: Homepage, https://github.com/alexander-forster/cohdl_sim
Classifier: Programming Language :: Python :: 3
Classifier: License :: OSI Approved :: MIT License
Requires-Python: >=3.11
License-File: LICENSE
Requires-Dist: cohdl==0.2.4
Requires-Dist: cocotb==1.9.0
Requires-Dist: cocotb_test==0.2.5
Dynamic: author
Dynamic: license-file
